tululu_offline/__init__.py
tululu_offline/app.py
tululu_offline/book.py
tululu_offline/download_files.py
tululu_offline/get_args.py
tululu_offline/parse_tululu_category.py
tululu_offline/render_website.py
tululu_offline/template/images/android-chrome-192x192.png
tululu_offline/template/images/android-chrome-512x512.png
tululu_offline/template/images/apple-touch-icon.png
tululu_offline/template/images/favicon-16x16.png
tululu_offline/template/images/favicon-32x32.png
tululu_offline/template/images/favicon.ico
tululu_offline/template/images/mstile-150x150.png
tululu_offline/template/images/safari-pinned-tab.svg
tululu_offline/template/index.html
tululu_offline/template/static/css/bootstrap.min.css
tululu_offline/template/static/js/bootstrap.min.js
tululu_offline/template/static/js/jquery-3.4.1.slim.min.js
tululu_offline/template/static/js/popper.min.js
tululu_offline-1.0.6.dist-info/entry_points.txt
tululu_offline-1.0.6.dist-info/LICENSE
tululu_offline-1.0.6.dist-info/WHEEL
tululu_offline-1.0.6.dist-info/METADATA
tululu_offline-1.0.6.dist-info/RECORD
