Metadata-Version: 2.1
Name: tululu-offline
Version: 1.0.6
Summary: Read it tululu.org without Internet
Home-page: https://github.com/velivir/tululu-offline
License: MIT
Author: Vitaliy Antonov
Author-email: vitaliyantonoff@gmail.com
Requires-Python: >=3.7,<4.0
Classifier: License :: OSI Approved :: MIT License
Classifier: Programming Language :: Python :: 3
Classifier: Programming Language :: Python :: 3.7
Classifier: Programming Language :: Python :: 3.8
Requires-Dist: BeautifulSoup4 (>=4.8.2,<5.0.0)
Requires-Dist: Jinja2 (>=2.11.1,<3.0.0)
Requires-Dist: livereload (>=2.6.1,<3.0.0)
Requires-Dist: lxml (>=4.5.0,<5.0.0)
Requires-Dist: more-itertools (>=8.3.0,<9.0.0)
Requires-Dist: pathvalidate (>=2.2.0,<3.0.0)
Requires-Dist: requests (>=2.23.0,<3.0.0)
Requires-Dist: tqdm (>=4.43.0,<5.0.0)
Project-URL: Repository, https://github.com/velivir/tululu-offline
